AUTHORS.rst
CONTRIBUTING.rst
HISTORY.rst
LICENSE
MANIFEST.in
README.rst
setup.cfg
setup.py
docs/Makefile
docs/authors.rst
docs/conf.py
docs/contributing.rst
docs/history.rst
docs/index.rst
docs/installation.rst
docs/make.bat
docs/modules.rst
docs/palpatine.rst
docs/readme.rst
docs/usage.rst
palpatine/__init__.py
palpatine/const.py
palpatine/cursor.py
palpatine/line.py
palpatine/screen.py
palpatine/utils.py
palpatine.egg-info/PKG-INFO
palpatine.egg-info/SOURCES.txt
palpatine.egg-info/dependency_links.txt
palpatine.egg-info/not-zip-safe
palpatine.egg-info/top_level.txt
tests/__init__.py
tests/test_cursor.py
tests/utils.py