Metadata-Version: 1.1
Name: palpatine
Version: 0.1.0
Summary: Manipulate your console screen like an emperor.
Home-page: https://github.com/uranusjr/palpatine
Author: Tzu-ping Chung
Author-email: uranusjr@gmail.com
License: BSD
Keywords: palpatine
Platform: UNKNOWN
Classifier: Development Status :: 2 - Pre-Alpha
Classifier: Intended Audience :: Developers
Classifier: License :: OSI Approved :: BSD License
Classifier: Natural Language :: English
Classifier: Programming Language :: Python :: 2
Classifier: Programming Language :: Python :: 2.6
Classifier: Programming Language :: Python :: 2.7
Classifier: Programming Language :: Python :: 3
Classifier: Programming Language :: Python :: 3.3
Classifier: Programming Language :: Python :: 3.4
